pysr_container/__init__.py
pysr_container/container.py
pysr_container/contract/__init__.py
pysr_container/contract/definition.py
pysr_container/definitions/__init__.py
pysr_container/definitions/object.py
pysr_container/definitions/reference.py
pysr_container/definitions/value.py
pysr_container/exceptions.py
pysr_container/resolvers/__init__.py
pysr_container/resolvers/arguments.py
pysr_container/resolvers/function.py
pysr_container/resolvers/object.py
pysr_container/resolvers/resolved/__init__.py
pysr_container/resolvers/resolved/function.py
pysr_container/stack.py
pysr_container-0.1.1.dist-info/METADATA
pysr_container-0.1.1.dist-info/WHEEL
pysr_container-0.1.1.dist-info/RECORD
