Metadata-Version: 2.1
Name: pysr-container
Version: 0.1.1
Summary: Реализация контейнера внедрения зависимостей pysr-abc-container 1.0
Author: Alexey Volkov
Author-email: webwizardry@hotmail.com
Requires-Python: >=3.12,<4.0
Classifier: Programming Language :: Python :: 3
Classifier: Programming Language :: Python :: 3.12
Requires-Dist: pysr-abc-container (>=0.1,<0.2)
